zvamz/__init__.py
zvamz/amz_listing_update.py
zvamz/api.py
zvamz/cretio_report.py
zvamz/fc_address.py
zvamz/fcmap.py
zvamz/gmail_automation.py
zvamz/h10_automation.py
zvamz/instacart_report.py
zvamz/kroger.py
zvamz/marketplaces.py
zvamz/ratelimit.py
zvamz/reports.py
zvamz/spapi_daterange_reports.py
zvamz/walmart_report.py
zvamz-0.0.132.dist-info/METADATA
zvamz-0.0.132.dist-info/WHEEL
zvamz-0.0.132.dist-info/RECORD
